LICENSE
README.txt
setup.py
memhive/__init__.py
memhive/_version.py
memhive/asyncio.py
memhive/memhive.py
memhive.egg-info/PKG-INFO
memhive.egg-info/SOURCES.txt
memhive.egg-info/dependency_links.txt
memhive.egg-info/requires.txt
memhive.egg-info/top_level.txt
memhive/core/map.c
memhive/core/memhive.c
memhive/core/module.c
memhive/core/queue.c
memhive/core/refqueue.c
memhive/core/sub.c
memhive/core/track.c
memhive/core/utils.c